ChangeLog.txt
LICENSE.txt
MANIFEST.in
setup.py
tnetstring/__init__.py
tnetstring/_tnetstring.c
tnetstring/dbg.h
tnetstring/tns_core.c
tnetstring/tns_core.h
tnetstring3.egg-info/PKG-INFO
tnetstring3.egg-info/SOURCES.txt
tnetstring3.egg-info/dependency_links.txt
tnetstring3.egg-info/top_level.txt