Metadata-Version: 1.1
Name: tnetstring3
Version: 0.3.1
Summary: Super fast data serialization for Python 3
Home-page: http://github.com/carlopires/tnetstring3
Author: Carlo Pires
Author-email: carlopires@gmail
License: MIT
Keywords: netstring serialization
Platform: UNKNOWN
Classifier: Programming Language :: Python
Classifier: Programming Language :: Python :: 3
Classifier: Development Status :: 4 - Beta
Classifier: License :: OSI Approved :: MIT License
